{"840":{"Path":["7","10","10","840"],"Coordinates":[-0.40263278049369994,0.52435462898753682,-0.13925384912957398],"Categories":["Citeromyces matritensis","Citeromyces matritensis","Citeromyces","Saccharomycetaceae","Saccharomycetales"],"Properties":[-4,4,-1]},"1041":{"Path":["7","10","10","840"],"Coordinates":[-0.400576357667246,0.52351692816296791,-0.13628858585536949],"Categories":["Wickerhamia fluorescens","Wickerhamia fluorescens","Wickerhamia","Saccharomycodaceae","Saccharomycetales"],"Properties":[-4,4,-1]},"2244":{"Path":["7","10","10","840"],"Coordinates":[-0.40442482663323387,0.52075024229398015,-0.14264293634359418],"Categories":["Trichosporon dermatis","Trichosporon mucoides","Trichosporon","Trichosporonaceae","Tremellales"],"Properties":[-4,4,-1]},"4082":{"Path":["7","10","10","840"],"Coordinates":[-0.40255764255720156,0.526247129444721,-0.13632153937652655],"Categories":["Rhodotorula taiwanensis","Rhodotorula taiwanensis","Rhodotorula","","Sporidiobolales"],"Properties":[-4,4,-1]}}