{"506":{"Path":["9","9","58","506"],"Coordinates":[-0.38486563532577284,0.42537553826449342,-0.20888608632024536],"Categories":["Saccharomyces pastorianus","Saccharomyces pastorianus","Saccharomyces","Saccharomycetaceae","Saccharomycetales"],"Properties":[-3,3,-1]},"1160":{"Path":["9","9","58","506"],"Coordinates":[-0.38029350754026958,0.42726413454955081,-0.21128058561923779],"Categories":["Rhodotorula foliorum","Rhodotorula foliorum","Rhodotorula","","Sporidiobolales"],"Properties":[-3,3,-1]},"1241":{"Path":["9","9","58","506"],"Coordinates":[-0.38196256161662467,0.42584570832677904,-0.21166816197522465],"Categories":["Trichosporon scarabaeorum","Trichosporon scarabaeorum","Trichosporon","Trichosporonaceae","Tremellales"],"Properties":[-3,3,-1]},"1404":{"Path":["9","9","58","506"],"Coordinates":[-0.38171922502878197,0.42858426065016991,-0.2104993360925283],"Categories":["Trichosporon asahii","Trichosporon aquatile","Trichosporon","Trichosporonaceae","Tremellales"],"Properties":[-3,3,-1]},"1648":{"Path":["9","9","58","506"],"Coordinates":[-0.3862967458829642,0.42235096312536047,-0.20422140047295634],"Categories":["Candida multigemmis","Candida multigemmis","Candida","","Saccharomycetales"],"Properties":[-3,3,-1]},"3535":{"Path":["9","9","58","506"],"Coordinates":[-0.38886486383799185,0.42745677021156825,-0.21227748038667826],"Categories":["Bensingtonia pseudonaganoensis","Bensingtonia pseudonaganoensis","Bensingtonia","Agaricostilbaceae","Agaricostilbales"],"Properties":[-3,3,-1]},"3687":{"Path":["9","9","58","506"],"Coordinates":[-0.38811877636824194,0.42886059316225117,-0.21195780507010181],"Categories":["Candida labiduridarum","Candida labiduridarum","Candida","","Saccharomycetales"],"Properties":[-3,3,-1]}}