{"3171":{"Path":["0","3171","3171","3171"],"Coordinates":[0.774068502789221,0.93510084200368893,0.45942278026871614],"Categories":["Malassezia yamatoensis","Malassezia yamatoensis","Malassezia","","Malasseziales"],"Properties":[7,7,4]},"3172":{"Path":["0","3171","3171","3171"],"Coordinates":[0.77164339685361472,0.93470401304200856,0.46489647993096861],"Categories":["Malassezia yamatoensis","Malassezia yamatoensis","Malassezia","","Malasseziales"],"Properties":[7,7,4]},"3173":{"Path":["0","3171","3171","3171"],"Coordinates":[0.77164256230175754,0.93470387648192355,0.46489836359496156],"Categories":["Malassezia yamatoensis","Malassezia yamatoensis","Malassezia","","Malasseziales"],"Properties":[7,7,4]}}