{"143":{"Path":["2","2","143","143"],"Coordinates":[-0.30413379755591186,0.39783917892627074,0.066001299175621364],"Categories":["Hanseniaspora uvarum","Hanseniaspora uvarum","Hanseniaspora","Saccharomycodaceae","Saccharomycetales"],"Properties":[-3,3,0]},"341":{"Path":["2","2","143","341"],"Coordinates":[-0.2922434167847956,0.40264206495485683,0.062402469696563344],"Categories":["Candida parapsilosis","Candida parapsilosis","Candida","","Saccharomycetales"],"Properties":[-2,3,0]},"497":{"Path":["2","2","143","497"],"Coordinates":[-0.29730265731598771,0.38888085083564528,0.0760959938034025],"Categories":["Saccharomyces pastorianus","Saccharomyces pastorianus","Saccharomyces","Saccharomycetaceae","Saccharomycetales"],"Properties":[-2,3,0]},"531":{"Path":["2","2","143","531"],"Coordinates":[-0.308000105079263,0.39110669212860349,0.060492944302616591],"Categories":["Kazachstania pintolopesii","Kazachstania pintolopesii","Kazachstania","Saccharomycetaceae","Saccharomycetales"],"Properties":[-3,3,0]},"730":{"Path":["2","2","143","730"],"Coordinates":[-0.29515292295907791,0.39948044971021263,0.053173873514171237],"Categories":["Rhodotorula marina","Rhodotorula marina","Rhodotorula","","Sporidiobolales"],"Properties":[-2,3,0]}}