{"81":{"Path":["7","7","81","81"],"Coordinates":[-0.50127532329896674,0.56052939464565543,-0.1494100644603811],"Categories":["Candida gropengiesseri","Candida gropengiesseri","Candida","","Saccharomycetales"],"Properties":[-5,4,-1]},"1917":{"Path":["7","7","81","81"],"Coordinates":[-0.50189201950405959,0.563949646383454,-0.1474425280889467],"Categories":["Sporobolomyces kluyveri-nielii","Sporobolomyces kluyveri-nielii","Sporobolomyces","","Sporidiobolales"],"Properties":[-5,4,-1]},"3167":{"Path":["7","7","81","81"],"Coordinates":[-0.50193951856721808,0.56350811246632515,-0.14643334561136331],"Categories":["Candida galli","Candida galli","Candida","","Saccharomycetales"],"Properties":[-5,4,-1]},"3194":{"Path":["7","7","81","81"],"Coordinates":[-0.49801129643500491,0.55656817779970591,-0.15023841076123273],"Categories":["Metschnikowia colocasiae","Metschnikowia colocasiae","Metschnikowia","Metschnikowiaceae","Saccharomycetales"],"Properties":[-4,4,-1]},"4097":{"Path":["7","7","81","81"],"Coordinates":[-0.49982103475001877,0.55860999914994092,-0.14730294807181985],"Categories":["Cystobasidium psychroaquaticum","Cystobasidium psychroaquaticum","Cystobasidium","Platygloeaceae","Platygloeales"],"Properties":[-4,4,-1]}}