{"1421":{"Path":["0","0","1421","1421"],"Coordinates":[0.54204944725038207,0.42341218464671015,0.286912103098121],"Categories":["Candida odintsovae","Candida odintsovae","Candida","","Saccharomycetales"],"Properties":[5,3,2]},"1727":{"Path":["0","0","1421","1727"],"Coordinates":[0.55260823194947717,0.32599840298880656,0.51817503665488585],"Categories":["Wickerhamomyces rabaulensis","Wickerhamomyces rabaulensis","Wickerhamomyces","","Saccharomycetales"],"Properties":[5,2,4]},"1728":{"Path":["0","0","1421","1728"],"Coordinates":[0.54616010656415137,0.36313451165571586,0.50807277972239318],"Categories":["Wickerhamomyces rabaulensis","Wickerhamomyces rabaulensis","Wickerhamomyces","","Saccharomycetales"],"Properties":[5,2,4]}}