{"2189":{"Path":["0","0","2189","2189"],"Coordinates":[0.57941199147338263,0.53579869589526186,0.688383519748618],"Categories":["Sporobolomyces lactophilus","Sporobolomyces lactophilus","Sporobolomyces","","Sporidiobolales"],"Properties":[5,4,6]},"2190":{"Path":["0","0","2189","2189"],"Coordinates":[0.578213801397463,0.53696233155895012,0.68692312355288587],"Categories":["Sporobolomyces lactophilus","Sporobolomyces lactophilus","Sporobolomyces","","Sporidiobolales"],"Properties":[5,4,6]},"2191":{"Path":["0","0","2189","2189"],"Coordinates":[0.57803231161062107,0.537137827699624,0.68670283944727906],"Categories":["Sporobolomyces lactophilus","Sporobolomyces lactophilus","Sporobolomyces","","Sporidiobolales"],"Properties":[5,4,6]},"2192":{"Path":["0","0","2189","2189"],"Coordinates":[0.57810346749001884,0.53706920985279849,0.6867890890013939],"Categories":["Sporobolomyces lactophilus","Sporobolomyces lactophilus","Sporobolomyces","","Sporidiobolales"],"Properties":[5,4,6]},"2193":{"Path":["0","0","2189","2189"],"Coordinates":[0.57793997954339293,0.53722792798444463,0.68658988583522085],"Categories":["Sporobolomyces lactophilus","Sporobolomyces lactophilus","Sporobolomyces","","Sporidiobolales"],"Properties":[5,4,6]},"2194":{"Path":["0","0","2189","2189"],"Coordinates":[0.57792737035179731,0.5372405588601803,0.68657392264649963],"Categories":["Sporobolomyces lactophilus","Sporobolomyces lactophilus","Sporobolomyces","","Sporidiobolales"],"Properties":[5,4,6]}}