{"3833":{"Path":["0","0","3833","3833"],"Coordinates":[0.52102276070348208,0.67170371291335162,0.43659659915443078],"Categories":["Candida oxycetoniae","Candida oxycetoniae","Candida","","Saccharomycetales"],"Properties":[5,5,3]},"3834":{"Path":["0","0","3833","3833"],"Coordinates":[0.55623422104859443,0.644000115122084,0.43755994487175115],"Categories":["Candida oxycetoniae","Candida oxycetoniae","Candida","","Saccharomycetales"],"Properties":[5,5,3]},"3835":{"Path":["0","0","3833","3833"],"Coordinates":[0.55060144476821493,0.64843185884956278,0.43740583848555925],"Categories":["Candida oxycetoniae","Candida oxycetoniae","Candida","","Saccharomycetales"],"Properties":[5,5,3]},"3836":{"Path":["0","0","3833","3833"],"Coordinates":[0.61880691002556376,0.59476930813066986,0.43927186284835257],"Categories":["Candida oxycetoniae","Candida oxycetoniae","Candida","","Saccharomycetales"],"Properties":[6,4,3]}}