{"682":{"Path":["5","19","19","682"],"Coordinates":[-0.52802229573899162,0.40735233624876332,-0.1051234564591258],"Categories":["Torulaspora pretoriensis","Torulaspora pretoriensis","Torulaspora","Saccharomycetaceae","Saccharomycetales"],"Properties":[-5,3,0]},"1338":{"Path":["5","19","19","682"],"Coordinates":[-0.52509279785769258,0.40817736781364466,-0.11040635473049049],"Categories":["Sporidiobolus ruineniae","Sporidiobolus ruineniae","Sporidiobolus","Sporidiobolaceae","Sporidiobolales"],"Properties":[-5,3,0]},"2514":{"Path":["5","19","19","682"],"Coordinates":[-0.53040609616269108,0.40624882814913,-0.10799112530899438],"Categories":["Eremothecium sinecaudum","Eremothecium sinecaudum","Eremothecium","Eremotheciaceae","Saccharomycetales"],"Properties":[-5,3,0]},"2608":{"Path":["5","19","19","682"],"Coordinates":[-0.52533158682770631,0.40801321588505945,-0.10808651999081993],"Categories":["Kurtzmanomyces insolitus","Kurtzmanomyces insolitus","Kurtzmanomyces","Chionosphaeraceae","Agaricostilbales"],"Properties":[-5,3,0]},"3068":{"Path":["5","19","19","682"],"Coordinates":[-0.52687762468565469,0.40408658878913734,-0.10349086223933494],"Categories":["Candida kipukae","Candida kipukae","Candida","","Saccharomycetales"],"Properties":[-5,3,0]}}