{"3822":{"Path":["0","0","3822","3822"],"Coordinates":[0.77435733042920785,0.84456182320933637,0.20798990723514527],"Categories":["Candida khaoyaiensis","Candida khaoyaiensis","Candida","","Saccharomycetales"],"Properties":[7,6,1]},"3823":{"Path":["0","0","3822","3822"],"Coordinates":[0.77974867716508867,0.8479412670620895,0.21090741116479306],"Categories":["Candida khaoyaiensis","Candida khaoyaiensis","Candida","","Saccharomycetales"],"Properties":[7,6,1]},"3824":{"Path":["0","0","3822","3822"],"Coordinates":[0.77126945937394742,0.84263139756732885,0.20633486790109409],"Categories":["Candida khaoyaiensis","Candida khaoyaiensis","Candida","","Saccharomycetales"],"Properties":[7,6,1]}}