{"2974":{"Path":["0","0","2544","2974"],"Coordinates":[0.46604361755936013,0.37638328557814221,0.68200058479118686],"Categories":["Kockovaella calophylli","Kockovaella calophylli","Kockovaella","Cuniculitremaceae","Tremellales"],"Properties":[4,3,6]},"2975":{"Path":["0","0","2544","2974"],"Coordinates":[0.46448776005307363,0.37328459595451013,0.68000623935386839],"Categories":["Kockovaella calophylli","Kockovaella calophylli","Kockovaella","Cuniculitremaceae","Tremellales"],"Properties":[4,2,6]},"2976":{"Path":["0","0","2544","2974"],"Coordinates":[0.46448148600499589,0.37329209627395249,0.67999950971982015],"Categories":["Kockovaella calophylli","Kockovaella calophylli","Kockovaella","Cuniculitremaceae","Tremellales"],"Properties":[4,2,6]},"2977":{"Path":["0","0","2544","2974"],"Coordinates":[0.46447486384125997,0.37330006668647736,0.6799924102326641],"Categories":["Kockovaella calophylli","Kockovaella calophylli","Kockovaella","Cuniculitremaceae","Tremellales"],"Properties":[4,2,6]}}