{"680":{"Path":["5","19","146","680"],"Coordinates":[-0.50713041884794974,0.41557490120763035,-0.11720329381110438],"Categories":["Torulaspora pretoriensis","Torulaspora pretoriensis","Torulaspora","Saccharomycetaceae","Saccharomycetales"],"Properties":[-5,3,-1]},"1848":{"Path":["5","19","146","680"],"Coordinates":[-0.50427971473018685,0.41530878544985855,-0.11880006305170975],"Categories":["Myxozyma mucilagina","Myxozyma mucilagina","Myxozyma","Lipomycetaceae","Saccharomycetales"],"Properties":[-5,3,-1]},"2989":{"Path":["5","19","146","680"],"Coordinates":[-0.50699074419285317,0.42101198983756277,-0.117883437097894],"Categories":["Bannoa hahajimensis","Bannoa hahajimensis","Bannoa","","Erythrobasidiales"],"Properties":[-5,3,-1]},"3919":{"Path":["5","19","146","680"],"Coordinates":[-0.50444230684040892,0.41618152545344633,-0.11861318936150928],"Categories":["Candida sekii","Candida sekii","Candida","","Saccharomycetales"],"Properties":[-5,3,-1]}}