{"1324":{"Path":["0","1324","1324","1324"],"Coordinates":[0.55886411581177386,0.62459814018697146,0.41662300472466596],"Categories":["Sporopachydermia lactativora","Sporopachydermia lactativora","Sporopachydermia","","Saccharomycetales"],"Properties":[5,4,3]},"1687":{"Path":["0","1324","1687","1687"],"Coordinates":[0.44311125770788828,0.85027365480645478,0.56607503129202941],"Categories":["Sporopachydermia cereana","Sporopachydermia cereana","Sporopachydermia","","Saccharomycetales"],"Properties":[4,6,5]},"2413":{"Path":["0","1324","2413","2413"],"Coordinates":[0.49656826858917996,0.7180624537490613,0.6325200286802054],"Categories":["Sporopachydermia quercuum","Sporopachydermia quercuum","Sporopachydermia","","Saccharomycetales"],"Properties":[4,5,5]}}