{"3759":{"Path":["0","0","3761","3761"],"Coordinates":[0.48151496427613893,0.56347810748919669,0.40118783020862281],"Categories":["Candida musiphila","Candida musiphila","Candida","","Saccharomycetales"],"Properties":[4,4,3]},"3760":{"Path":["0","0","3761","3761"],"Coordinates":[0.48280785023690759,0.56006670473646269,0.39396950825523369],"Categories":["Candida musiphila","Candida musiphila","Candida","","Saccharomycetales"],"Properties":[4,4,3]},"3761":{"Path":["0","0","3761","3761"],"Coordinates":[0.48142658083983175,0.56371131559546017,0.4016812844482387],"Categories":["Candida musiphila","Candida musiphila","Candida","","Saccharomycetales"],"Properties":[4,4,3]}}