{"1086":{"Path":["0","0","1089","1089"],"Coordinates":[0.60917278661805951,0.55173856488416462,0.51455317862701522],"Categories":["Saturnispora saitoi","Saturnispora saitoi","Saturnispora","Saccharomycetaceae","Saccharomycetales"],"Properties":[6,4,4]},"1087":{"Path":["0","0","1089","1089"],"Coordinates":[0.60897797897134831,0.55217369516169179,0.51411799293212046],"Categories":["Saturnispora saitoi","Saturnispora saitoi","Saturnispora","Saccharomycetaceae","Saccharomycetales"],"Properties":[6,4,4]},"1088":{"Path":["0","0","1089","1089"],"Coordinates":[0.608830409222208,0.55250331295173116,0.51378833316266825],"Categories":["Saturnispora saitoi","Saturnispora saitoi","Saturnispora","Saccharomycetaceae","Saccharomycetales"],"Properties":[6,4,4]},"1089":{"Path":["0","0","1089","1089"],"Coordinates":[0.6086692432012949,0.55286329992662986,0.51342830034052744],"Categories":["Saturnispora saitoi","Saturnispora saitoi","Saturnispora","Saccharomycetaceae","Saccharomycetales"],"Properties":[6,4,4]}}