{"258":{"Path":["0","0","258","258"],"Coordinates":[0.28704835410289742,0.50869435584447587,0.40944970013610349],"Categories":["Sporidiobolus pararoseus","Sporidiobolus pararoseus","Sporidiobolus","Sporidiobolaceae","Sporidiobolales"],"Properties":[2,4,3]},"270":{"Path":["0","0","258","270"],"Coordinates":[0.8057091076627354,0.485462854977201,0.36112614947692667],"Categories":["Sporobolomyces salmoneus","Sporobolomyces salmoneus","Sporobolomyces","","Sporidiobolales"],"Properties":[8,3,3]},"947":{"Path":["0","0","258","947"],"Coordinates":[0.47836427209195936,0.67253746143326165,0.46968623013705729],"Categories":["Sporobolomyces carnicolor","Sporobolomyces carnicolor","Sporobolomyces","","Sporidiobolales"],"Properties":[4,5,4]},"1299":{"Path":["0","0","258","1299"],"Coordinates":[0.72075639386635226,0.6279526628758515,0.49040386364254374],"Categories":["Sporobolomyces japonicus","Sporobolomyces japonicus","Sporobolomyces","","Sporidiobolales"],"Properties":[7,5,4]},"3041":{"Path":["0","0","258","3041"],"Coordinates":[0.39914071276844726,0.28579525630183933,0.43720144698320024],"Categories":["Sporobolomyces phaffii","Sporobolomyces phaffii","Sporobolomyces","","Sporidiobolales"],"Properties":[3,2,3]},"3085":{"Path":["0","0","258","3085"],"Coordinates":[0.50561204921268954,0.73001158611606154,0.71407595286743664],"Categories":["Sporobolomyces nakasei","Sporobolomyces nakasei","Sporobolomyces","","Sporidiobolales"],"Properties":[5,5,6]}}