{"1453":{"Path":["0","0","1455","1455"],"Coordinates":[0.41152254664008775,0.505060017856555,0.56146552270179118],"Categories":["Blastobotrys chiropterorum","Blastobotrys chiropterorum","Blastobotrys","Trichomonascaceae","Saccharomycetales"],"Properties":[4,4,5]},"1454":{"Path":["0","0","1455","1455"],"Coordinates":[0.41257270499487264,0.505512328689282,0.56065516085991851],"Categories":["Blastobotrys chiropterorum","Blastobotrys chiropterorum","Blastobotrys","Trichomonascaceae","Saccharomycetales"],"Properties":[4,4,5]},"1455":{"Path":["0","0","1455","1455"],"Coordinates":[0.41173794814991926,0.505152792851715,0.56129930666070049],"Categories":["Blastobotrys chiropterorum","Blastobotrys chiropterorum","Blastobotrys","Trichomonascaceae","Saccharomycetales"],"Properties":[4,4,5]}}