{"2152":{"Path":["0","0","3963","2152"],"Coordinates":[0.48456758231247804,0.70008618352645047,0.70065766112322059],"Categories":["Sporobolomyces ruber","Sporobolomyces ruber","Sporobolomyces","","Sporidiobolales"],"Properties":[4,5,6]},"2153":{"Path":["0","0","3963","2152"],"Coordinates":[0.48417466076623933,0.69940934743743721,0.7005551544265527],"Categories":["Sporobolomyces ruber","Sporobolomyces ruber","Sporobolomyces","","Sporidiobolales"],"Properties":[4,5,6]},"2154":{"Path":["0","0","3963","2152"],"Coordinates":[0.48425185253860564,0.69954625227217659,0.70059098676027576],"Categories":["Sporobolomyces ruber","Sporobolomyces ruber","Sporobolomyces","","Sporidiobolales"],"Properties":[4,5,6]},"2155":{"Path":["0","0","3963","2152"],"Coordinates":[0.48403399583822138,0.69915919396548654,0.70048998440233079],"Categories":["Sporobolomyces ruber","Sporobolomyces ruber","Sporobolomyces","","Sporidiobolales"],"Properties":[4,5,6]},"2156":{"Path":["0","0","3963","2152"],"Coordinates":[0.48383090362488212,0.69881743063448831,0.70046913281258161],"Categories":["Sporobolomyces ruber","Sporobolomyces ruber","Sporobolomyces","","Sporidiobolales"],"Properties":[4,5,6]},"2157":{"Path":["0","0","3963","2152"],"Coordinates":[0.48382943492559277,0.69882280960243315,0.70049072726501882],"Categories":["Sporobolomyces ruber","Sporobolomyces ruber","Sporobolomyces","","Sporidiobolales"],"Properties":[4,5,6]}}