{"98":{"Path":["4","27","98","98"],"Coordinates":[-0.56564412295631616,0.66849369264667613,-0.040202030411151814],"Categories":["Cryptococcus diffluens","Cryptococcus diffluens","Cryptococcus","Tremellaceae","Tremellales"],"Properties":[-5,5,0]},"325":{"Path":["4","27","98","325"],"Coordinates":[-0.56475906316778191,0.65823098741546815,-0.050426786869584551],"Categories":["Cryptococcus humicola","Cryptococcus humicola","Cryptococcus","Tremellaceae","Tremellales"],"Properties":[-5,5,0]},"449":{"Path":["4","27","98","449"],"Coordinates":[-0.553306083432616,0.66240576041980925,-0.043334568433369372],"Categories":["Debaryomyces hansenii","Debaryomyces fabryi","Debaryomyces","Saccharomycetaceae","Saccharomycetales"],"Properties":[-5,5,0]},"681":{"Path":["4","27","98","681"],"Coordinates":[-0.55718242153579856,0.65825321094189171,-0.040306749703775756],"Categories":["Torulaspora pretoriensis","Torulaspora pretoriensis","Torulaspora","Saccharomycetaceae","Saccharomycetales"],"Properties":[-5,5,0]}}