{"103":{"Path":["3","46","103","103"],"Coordinates":[-0.31869000963970767,0.2645530381257517,-0.15001148939060055],"Categories":["Candida magnoliae","Candida magnoliae","Candida","","Saccharomycetales"],"Properties":[-3,2,-1]},"551":{"Path":["3","46","103","551"],"Coordinates":[-0.33321062481702041,0.25925694074766731,-0.14848263003462964],"Categories":["Trichosporon debeurmannianum","Trichosporon debeurmannianum","Trichosporon","Trichosporonaceae","Tremellales"],"Properties":[-3,2,-1]},"645":{"Path":["3","46","103","645"],"Coordinates":[-0.31195770369242709,0.25513604681169366,-0.15078195001741482],"Categories":["Vanderwaltozyma polyspora","Vanderwaltozyma polyspora","Vanderwaltozyma","Saccharomycetaceae","Saccharomycetales"],"Properties":[-3,2,-1]},"801":{"Path":["3","46","103","801"],"Coordinates":[-0.32733164063147674,0.266078009030408,-0.15627410201170888],"Categories":["Lodderomyces elongisporus","Lodderomyces elongisporus","Lodderomyces","Saccharomycetaceae","Saccharomycetales"],"Properties":[-3,2,-1]}}