{"2010":{"Path":["0","0","2010","2010"],"Coordinates":[0.56964458975791565,0.53346383210925818,0.544975814488739],"Categories":["Bensingtonia yamatoana","Bensingtonia yamatoana","Bensingtonia","Agaricostilbaceae","Agaricostilbales"],"Properties":[5,4,4]},"2011":{"Path":["0","0","2010","2011"],"Coordinates":[0.38802654433557376,0.47250804876500679,0.48821156230520685],"Categories":["Bensingtonia yamatoana","Bensingtonia yamatoana","Bensingtonia","Agaricostilbaceae","Agaricostilbales"],"Properties":[3,3,4]},"3097":{"Path":["0","0","2010","3097"],"Coordinates":[0.54997459434554474,0.39765594454770581,0.34986823768481856],"Categories":["Rhodotorula arctica","Rhodotorula arctica","Rhodotorula","","Sporidiobolales"],"Properties":[5,3,3]}}