{"289":{"Path":["0","0","293","293"],"Coordinates":[0.6049270077720631,0.65897457232069767,0.45760163608865634],"Categories":["Candida catenulata","Candida catenulata","Candida","","Saccharomycetales"],"Properties":[6,5,4]},"290":{"Path":["0","0","293","293"],"Coordinates":[0.60876819754697031,0.6586103730074554,0.4555214707218882],"Categories":["Candida catenulata","Candida catenulata","Candida","","Saccharomycetales"],"Properties":[6,5,4]},"291":{"Path":["0","0","293","293"],"Coordinates":[0.60591972407574857,0.65888039489550965,0.45706427041338865],"Categories":["Candida catenulata","Candida catenulata","Candida","","Saccharomycetales"],"Properties":[6,5,4]},"292":{"Path":["0","0","293","293"],"Coordinates":[0.6052285232346819,0.65894595992226213,0.45743845826649909],"Categories":["Candida catenulata","Candida catenulata","Candida","","Saccharomycetales"],"Properties":[6,5,4]},"293":{"Path":["0","0","293","293"],"Coordinates":[0.60504398558136,0.65896344387950434,0.457538448425069],"Categories":["Candida catenulata","Candida catenulata","Candida","","Saccharomycetales"],"Properties":[6,5,4]}}