{"107":{"Path":["9","9","107","107"],"Coordinates":[-0.37168009806184105,0.47877915102913277,-0.20623444602212973],"Categories":["Candida inconspicua","Candida inconspicua","Candida","","Saccharomycetales"],"Properties":[-3,3,-1]},"502":{"Path":["9","9","107","502"],"Coordinates":[-0.36477194818994707,0.46706650796877408,-0.1981824020586547],"Categories":["Saccharomyces pastorianus","Saccharomyces pastorianus","Saccharomyces","Saccharomycetaceae","Saccharomycetales"],"Properties":[-3,3,-1]},"728":{"Path":["9","9","107","728"],"Coordinates":[-0.37656851798725649,0.463470647726228,-0.20454328243310041],"Categories":["Rhodotorula marina","Rhodotorula marina","Rhodotorula","","Sporidiobolales"],"Properties":[-3,3,-1]},"731":{"Path":["9","9","107","731"],"Coordinates":[-0.37238562640389733,0.47480648034308581,-0.19639830833878108],"Categories":["Rhodotorula marina","Rhodotorula marina","Rhodotorula","","Sporidiobolales"],"Properties":[-3,3,-1]}}