{"670":{"Path":["2","48","145","670"],"Coordinates":[-0.26434590844261258,0.43609923404650613,0.096006286850379527],"Categories":["Kazachstania transvaalensis","Kazachstania transvaalensis","Kazachstania","Saccharomycetaceae","Saccharomycetales"],"Properties":[-2,3,0]},"1351":{"Path":["2","48","145","670"],"Coordinates":[-0.26383581884776547,0.43295813849581838,0.094991243169551931],"Categories":["Metschnikowia reukaufii","Metschnikowia reukaufii","Metschnikowia","Metschnikowiaceae","Saccharomycetales"],"Properties":[-2,3,0]},"1737":{"Path":["2","48","145","670"],"Coordinates":[-0.26198109079915466,0.4315249735040913,0.095057147621994728],"Categories":["Cryptococcus podzolicus","Cryptococcus podzolicus","Cryptococcus","Tremellaceae","Tremellales"],"Properties":[-2,3,0]},"2531":{"Path":["2","48","145","670"],"Coordinates":[-0.26471166911143307,0.43354241106716029,0.094883605051406986],"Categories":["Trichosporon gamsii","Trichosporon gamsii","Trichosporon","Trichosporonaceae","Tremellales"],"Properties":[-2,3,0]},"2900":{"Path":["2","48","145","670"],"Coordinates":[-0.26631182111503654,0.43576790728449677,0.098383005137010648],"Categories":["Saccharomyces mikatae","Saccharomyces mikatae","Saccharomyces","Saccharomycetaceae","Saccharomycetales"],"Properties":[-2,3,0]}}