{"4230":{"Path":["0","0","1566","4232"],"Coordinates":[0.53282863339741759,0.4487233905971828,0.37077375859776379],"Categories":["Lachancea lanzarotensis","Lachancea lanzarotensis","Lachancea","Saccharomycetaceae","Saccharomycetales"],"Properties":[5,3,3]},"4231":{"Path":["0","0","1566","4232"],"Coordinates":[0.53283756046801845,0.4487125298439868,0.37077453908223523],"Categories":["Lachancea lanzarotensis","Lachancea lanzarotensis","Lachancea","Saccharomycetaceae","Saccharomycetales"],"Properties":[5,3,3]},"4232":{"Path":["0","0","1566","4232"],"Coordinates":[0.53163518698586187,0.44762801441281735,0.37194659385759726],"Categories":["Lachancea lanzarotensis","Lachancea lanzarotensis","Lachancea","Saccharomycetaceae","Saccharomycetales"],"Properties":[5,3,3]},"4233":{"Path":["0","0","1566","4232"],"Coordinates":[0.53284195982551252,0.4487020118827873,0.37076594158026882],"Categories":["Lachancea lanzarotensis","Lachancea lanzarotensis","Lachancea","Saccharomycetaceae","Saccharomycetales"],"Properties":[5,3,3]},"4234":{"Path":["0","0","1566","4232"],"Coordinates":[0.53282904291688571,0.4487248541565797,0.37077616363194926],"Categories":["Lachancea lanzarotensis","Lachancea lanzarotensis","Lachancea","Saccharomycetaceae","Saccharomycetales"],"Properties":[5,3,3]},"4235":{"Path":["0","0","1566","4232"],"Coordinates":[0.53284071063529825,0.44870527994832116,0.37076981143786392],"Categories":["Lachancea lanzarotensis","Lachancea lanzarotensis","Lachancea","Saccharomycetaceae","Saccharomycetales"],"Properties":[5,3,3]},"4236":{"Path":["0","0","1566","4232"],"Coordinates":[0.5328363695771321,0.44871924991743556,0.37077724508624027],"Categories":["Lachancea lanzarotensis","Lachancea lanzarotensis","Lachancea","Saccharomycetaceae","Saccharomycetales"],"Properties":[5,3,3]},"4237":{"Path":["0","0","1566","4232"],"Coordinates":[0.53284287921031159,0.4487039163169293,0.370768443025443],"Categories":["Lachancea lanzarotensis","Lachancea lanzarotensis","Lachancea","Saccharomycetaceae","Saccharomycetales"],"Properties":[5,3,3]}}