{"749":{"Path":["7","24","24","749"],"Coordinates":[-0.52886699628082667,0.4553283193032327,-0.25493991588551118],"Categories":["Trichosporon moniliiforme","Trichosporon moniliiforme","Trichosporon","Trichosporonaceae","Tremellales"],"Properties":[-5,3,-2]},"1693":{"Path":["7","24","24","749"],"Coordinates":[-0.52465811114468464,0.45490954950748574,-0.25174067540178086],"Categories":["Yamadazyma philogaea","Yamadazyma philogaea","Yamadazyma","Saccharomycetaceae","Saccharomycetales"],"Properties":[-5,3,-2]},"2372":{"Path":["7","24","24","749"],"Coordinates":[-0.53065274750222879,0.45634949435388317,-0.25304329095467204],"Categories":["Malassezia globosa","Malassezia globosa","Malassezia","","Malasseziales"],"Properties":[-5,3,-2]},"2465":{"Path":["7","24","24","749"],"Coordinates":[-0.53005194386347954,0.45481724514135596,-0.25239928970396425],"Categories":["Cryptococcus vishniacii","Cryptococcus vishniacii","Cryptococcus","Tremellaceae","Tremellales"],"Properties":[-5,3,-2]}}