{"1513":{"Path":["0","0","1513","1513"],"Coordinates":[0.61256800330219707,0.41363992596552657,0.46514131434854095],"Categories":["Scheffersomyces ergatensis","Scheffersomyces ergatensis","Scheffersomyces","Debaryomycetaceae","Saccharomycetales"],"Properties":[6,3,4]},"1514":{"Path":["0","0","1513","1513"],"Coordinates":[0.612553120245664,0.41366413403134117,0.46510520157232027],"Categories":["Scheffersomyces ergatensis","Scheffersomyces ergatensis","Scheffersomyces","Debaryomycetaceae","Saccharomycetales"],"Properties":[6,3,4]},"1515":{"Path":["0","0","1513","1513"],"Coordinates":[0.61370585848836645,0.41246915458051769,0.46621615571699754],"Categories":["Scheffersomyces ergatensis","Scheffersomyces ergatensis","Scheffersomyces","Debaryomycetaceae","Saccharomycetales"],"Properties":[6,3,4]},"1516":{"Path":["0","0","1513","1513"],"Coordinates":[0.61256158635946856,0.41366645512040939,0.4650858445863309],"Categories":["Scheffersomyces ergatensis","Scheffersomyces ergatensis","Scheffersomyces","Debaryomycetaceae","Saccharomycetales"],"Properties":[6,3,4]}}