{"2086":{"Path":["0","0","2086","2086"],"Coordinates":[0.61055565384770849,0.47201884215316742,0.71938209154464738],"Categories":["Bullera variabilis","Bullera variabilis","Bullera","Tremellaceae","Tremellales"],"Properties":[6,3,6]},"2087":{"Path":["0","0","2086","2086"],"Coordinates":[0.61095798473548579,0.47235289675175574,0.72131293715342093],"Categories":["Bullera variabilis","Bullera variabilis","Bullera","Tremellaceae","Tremellales"],"Properties":[6,3,6]},"2088":{"Path":["0","0","2086","2086"],"Coordinates":[0.610954091692912,0.47237178291745646,0.72130995959025579],"Categories":["Bullera variabilis","Bullera variabilis","Bullera","Tremellaceae","Tremellales"],"Properties":[6,3,6]},"2089":{"Path":["0","0","2086","2086"],"Coordinates":[0.61134988129288348,0.47273704289799384,0.7232361086867265],"Categories":["Bullera variabilis","Bullera variabilis","Bullera","Tremellaceae","Tremellales"],"Properties":[6,3,6]},"2090":{"Path":["0","0","2086","2086"],"Coordinates":[0.61134064408545086,0.47278186875987482,0.72322892836688113],"Categories":["Bullera variabilis","Bullera variabilis","Bullera","Tremellaceae","Tremellales"],"Properties":[6,3,6]}}