{"651":{"Path":["8","8","120","651"],"Coordinates":[-0.56967226718678143,0.45488703021718035,0.066688203694135834],"Categories":["Vanderwaltozyma polyspora","Vanderwaltozyma polyspora","Vanderwaltozyma","Saccharomycetaceae","Saccharomycetales"],"Properties":[-5,3,0]},"1789":{"Path":["8","8","120","651"],"Coordinates":[-0.57430701226438063,0.45388242881297358,0.0665564712364542],"Categories":["Filobasidiella neoformans","Filobasidiella bacillispora","Filobasidiella","","Tremellales"],"Properties":[-5,3,0]},"2186":{"Path":["8","8","120","651"],"Coordinates":[-0.56647960692746413,0.4526763969440456,0.06830776854485246],"Categories":["Bullera miyagiana","Bullera miyagiana","Bullera","Tremellaceae","Tremellales"],"Properties":[-5,3,0]},"2582":{"Path":["8","8","120","651"],"Coordinates":[-0.56550963344974559,0.45146678176556337,0.069012533020451072],"Categories":["Fellomyces thailandicus","Fellomyces thailandicus","Fellomyces","Cuniculitremaceae","Tremellales"],"Properties":[-5,3,0]},"3754":{"Path":["8","8","120","651"],"Coordinates":[-0.56923655069717782,0.45076393981273349,0.065663647709732834],"Categories":["Kurtzmaniella cleridarum","Kurtzmaniella cleridarum","Kurtzmaniella","Saccharomycetaceae","Saccharomycetales"],"Properties":[-5,3,0]},"3854":{"Path":["8","8","120","651"],"Coordinates":[-0.56615863932993171,0.44985000499224981,0.067604881310813422],"Categories":["Candida sanitii","Candida sanitii","Candida","","Saccharomycetales"],"Properties":[-5,3,0]},"3921":{"Path":["8","8","120","651"],"Coordinates":[-0.57032039945364454,0.45096815568742976,0.07042118509914129],"Categories":["Candida uthaithanina","Candida uthaithanina","Candida","","Saccharomycetales"],"Properties":[-5,3,0]}}