{"1886":{"Path":["0","0","1886","1886"],"Coordinates":[0.532037587079996,0.39036808334904971,0.577361235465078],"Categories":["Kazachstania rosinii","Kazachstania rosinii","Kazachstania","Saccharomycetaceae","Saccharomycetales"],"Properties":[5,3,5]},"1887":{"Path":["0","0","1886","1886"],"Coordinates":[0.53204448231709567,0.39037924653239947,0.577358699421058],"Categories":["Kazachstania rosinii","Kazachstania rosinii","Kazachstania","Saccharomycetaceae","Saccharomycetales"],"Properties":[5,3,5]},"1888":{"Path":["0","0","1886","1886"],"Coordinates":[0.53203246159972017,0.39035978534924815,0.57736312059874728],"Categories":["Kazachstania rosinii","Kazachstania rosinii","Kazachstania","Saccharomycetaceae","Saccharomycetales"],"Properties":[5,3,5]}}